guided/__init__.py
guided/util.py
guided-0.0.6.dist-info/LICENSE
guided-0.0.6.dist-info/METADATA
guided-0.0.6.dist-info/WHEEL
guided-0.0.6.dist-info/top_level.txt
guided-0.0.6.dist-info/RECORD
