Metadata-Version: 2.1
Name: guided
Version: 0.0.6
Summary: Getting from diagramming to programming
Home-page: https://github.com/i2mint/guided
License: mit
Platform: any
License-File: LICENSE
Requires-Dist: graphviz
Requires-Dist: pydot
Requires-Dist: importlib-resources
